[
  { "word": "Ex", "hint": "Ayer" },
  { "word": "Crush", "hint": "Lejano" },
  { "word": "Cruda", "hint": "Cama" },
  { "word": "Aventura", "hint": "Veloz" },
  { "word": "Amante", "hint": "Noche" },
  { "word": "Friendzone", "hint": "Borde" },
  { "word": "Ghosting", "hint": "Vacio" },
  { "word": "Tinder", "hint": "Dedo" },
  { "word": "Red flag", "hint": "Color" },
  { "word": "Chisme", "hint": "Boca" },
  { "word": "Mentira", "hint": "Larga" },
  { "word": "Borracho", "hint": "Piso" },
  { "word": "Beso", "hint": "Boca" },
  { "word": "Coqueteo", "hint": "Ojos" },
  { "word": "Celos", "hint": "Mente" },
  { "word": "Infidelidad", "hint": "Dos" },
  { "word": "Tóxico", "hint": "Humo" },
  { "word": "OnlyFans", "hint": "Mes" },
  { "word": "Sugar Daddy", "hint": "Edad" },
  { "word": "Cita a ciegas", "hint": "Nudo" },
  { "word": "Chupetón", "hint": "Cuello" },
  { "word": "Stripper", "hint": "Barra" },
  { "word": "Trío", "hint": "Grupo" },
  { "main": "Gorda", "different": "Flaca" },
  { "main": "Diddy", "different": "Epstein" },
  { "main": "Hitler", "different": "Trump" },
  { "main": "Marihuana", "different": "Cocaina" },
  { "main": "Charlie Kirk", "different": "Tiroteo Escolar" },
  { "main": "Venezolanos", "different": "Peruanos" },
  { "main": "Orgia", "different": "Diddy" }
]