[
  {"word": "Pizza", "hint": "Caja"},
  {"word": "Hamburguesa", "hint": "Capas"},
  {"word": "Sushi", "hint": "Rollo"},
  {"word": "Tacos", "hint": "Doblado"},
  {"word": "Pasta", "hint": "Largo"},
  {"word": "Ensalada", "hint": "Bol"},
  {"word": "Sopa", "hint": "Líquido"},
  {"word": "Paella", "hint": "Sartén"},
  {"word": "Asado", "hint": "Humo"},
  {"word": "Ceviche", "hint": "Ácido"},
  {"word": "Ramen", "hint": "Cuenco"},
  {"word": "Burrito", "hint": "Manta"},
  {"word": "Hot dog", "hint": "Largo"},
  {"word": "Sándwich", "hint": "Corte"},
  {"word": "Lasagna", "hint": "Horno"},
  {"word": "Guacamole", "hint": "Verde"},
  {"word": "Hummus", "hint": "Crema"},
  {"word": "Curry", "hint": "Polvo"},
  {"word": "Empanada", "hint": "Cierre"},
  {"word": "Tortilla de patatas", "hint": "Redonda"},
  {"word": "Crepe", "hint": "Fina"},
  {"word": "Waffle", "hint": "Rejilla"},
  {"word": "Cereal", "hint": "Tazón"},
  {"word": "Manzana", "hint": "Árbol"},
  {"word": "Plátano", "hint": "Piel"},
  {"word": "Naranja", "hint": "Cáscara"},
  {"word": "Fresa", "hint": "Semillas"},
  {"word": "Uva", "hint": "Racimo"},
  {"word": "Sandía", "hint": "Peso"},
  {"word": "Piña", "hint": "Corona"},
  {"word": "Mango", "hint": "Fibra"},
  {"word": "Cereza", "hint": "Par"},
  {"word": "Limón", "hint": "Verde"},
  {"word": "Coco", "hint": "Agua"},
  {"word": "Kiwi", "hint": "Pelo"},
  {"word": "Zanahoria", "hint": "Tierra"},
  {"word": "Brócoli", "hint": "Ramas"},
  {"word": "Tomate", "hint": "Jugo"},
  {"word": "Cebolla", "hint": "Capas"},
  {"word": "Papa", "hint": "Tierra"},
  {"word": "Calabaza", "hint": "Naranja"},
  {"word": "Pepino", "hint": "Rodaja"},
  {"word": "Maíz", "hint": "Dientes"},
  {"word": "Champiñón", "hint": "Gorro"},
  {"word": "Frijol", "hint": "Semilla"},
  {"word": "Arroz", "hint": "Grano"},
  {"word": "Pan", "hint": "Miga"},
  {"word": "Croissant", "hint": "Luna"},
  {"word": "Galleta", "hint": "Caja"},
  {"word": "Pastel", "hint": "Velas"},
  {"word": "Chocolate", "hint": "Barra"},
  {"word": "Helado", "hint": "Copa"},
  {"word": "Donut", "hint": "Círculo"},
  {"word": "Churro", "hint": "Aceite"},
  {"word": "Mermelada", "hint": "Frasco"},
  {"word": "Miel", "hint": "Dorado"},
  {"word": "Sal", "hint": "Granos"},
  {"word": "Pimienta", "hint": "Negro"},
  {"word": "Ketchup", "hint": "Salsa"},
  {"word": "Vino", "hint": "Copa"},
  {"word": "Cerveza", "hint": "Espuma"},
  {"word": "Vodka", "hint": "Frío"},
  {"word": "Tequila", "hint": "Sal"},
  {"word": "Whisky", "hint": "Roca"},
  {"word": "Ron", "hint": "Caña"},
  {"word": "Champán", "hint": "Corcho"},
  {"word": "Agua", "hint": "Claro"},
  {"word": "Café", "hint": "Grano"},
  {"word": "Té", "hint": "Bolsa"},
  {"word": "Leche", "hint": "Cartón"},
  {"word": "Jugo", "hint": "Vaso"},
  {"word": "Limonada", "hint": "Hielo"},
  {"word": "Mojito", "hint": "Hielo"},
  {"word": "Queso", "hint": "Bloque"},
  {"word": "Huevo", "hint": "Nido"},
  {"word": "Tocino", "hint": "Grasa"}
]