[
  { "main": "¿Cuál es el invento de la humanidad que crees que más nos ha facilitado la vida?", "different": "¿Cuál es el invento de la humanidad que crees que deberíamos haber evitado a toda costa?" },
  { "main": "¿Cuál es la tradición o costumbre de tu país que te parece más absurda?", "different": "¿Cuál es el hábito de la gente en general que más te molesta en público?" },
  { "main": "Si tuvieras que elegir a una persona de este grupo para ir a una isla desierta, ¿en quién confiarías para sobrevivir?", "different": "Si tuvieras que elegir a una persona de este grupo para que sea tu socio en un crimen perfecto, ¿quién sería?" },
  { "main": "¿Cuál es el libro que crees que todo el mundo debería leer antes de morir?", "different": "¿Cuál es la película que crees que define perfectamente nuestra generación?" },
  { "main": "Si pudieras eliminar una enfermedad del mundo para siempre, ¿cuál elegirías?", "different": "Si pudieras hacer que una emoción negativa (ej. envidia) desaparezca de la humanidad, ¿cuál sería?" },
  { "main": "¿Cuál es el dato curioso o 'fun fact' más inútil que conoces?", "different": "¿Cuál es el misterio de la historia que más te gustaría resolver?" },
  { "main": "Si pudieras tener cualquier animal del mundo (salvaje o no) como mascota domesticada, ¿cuál elegirías?", "different": "Si pudieras convertirte en un animal por un día, ¿cuál sería el más divertido para espiar a la gente?" },
  { "main": "¿Cuál es la habilidad que crees que es esencial para sobrevivir en el mundo moderno?", "different": "¿Cuál es el consejo de vida que más has dado y que casi nunca aplicas para ti?" },
  { "main": "¿Cuál es el objeto de tu casa que salvarías primero en un incendio (después de seres vivos)?", "different": "¿Cuál es la posesión material de la que más te costaría deshacerte?" },
  { "main": "Si tuvieras que elegir a alguien del grupo para que sea el presidente de una nueva colonia en Marte, ¿quién sería?", "different": "Si tuvieras que elegir a alguien del grupo para que decida qué vas a comer todos los días por un mes, ¿en quién confiarías?" },
  { "main": "Si pudieras elegir una ley nueva para que se aplique en todo el mundo a partir de mañana, ¿cuál sería?", "different": "Si pudieras prohibir a la gente quejarse de una sola cosa, ¿qué elegirías?" }
]