[
  { "main": "PlayStation", "different": "Xbox" },
  { "main": "Mario", "different": "Sonic" },
  { "main": "Fortnite", "different": "Free Fire" },
  { "main": "Call of Duty", "different": "Battlefield" },
  { "main": "FIFA", "different": "eFootball" },
  { "main": "Minecraft", "different": "Roblox" },
  { "main": "League of Legends", "different": "Dota 2" },
  { "main": "GTA V", "different": "Red Dead Redemption" },
  { "main": "Zelda", "different": "Elden Ring" },
  { "main": "Among Us", "different": "Fall Guys" },
  { "main": "Nintendo Switch", "different": "Steam Deck" },
  { "main": "Game Boy", "different": "PSP" },
  { "main": "Tetris", "different": "Puyo Puyo" },
  { "main": "Street Fighter", "different": "Mortal Kombat" },
  { "main": "Tekken", "different": "SoulCalibur" },
  { "main": "Super Smash Bros", "different": "MultiVersus" },
  { "main": "Digimon", "different": "Pokémon" },
  { "main": "Resident Evil", "different": "Silent Hill" },
  { "main": "Final Fantasy", "different": "Dragon Quest" },
  { "main": "Kingdom Hearts", "different": "Disney Epic Mickey" },
  { "main": "The Sims", "different": "Animal Crossing" },
  { "main": "Halo", "different": "Destiny" },
  { "main": "Overwatch", "different": "Valorant" },
  { "main": "Apex Legends", "different": "Warzone" },
  { "main": "Counter-Strike", "different": "Rainbow Six Siege" },
  { "main": "Doom", "different": "Quake" },
  { "main": "Skyrim", "different": "The Witcher 3" },
  { "main": "Fallout", "different": "Starfield" },
  { "main": "Assassin's Creed", "different": "Ghost of Tsushima" },
  { "main": "God of War", "different": "Devil May Cry" },
  { "main": "Uncharted", "different": "Tomb Raider" },
  { "main": "The Last of Us", "different": "Days Gone" },
  { "main": "Dark Souls", "different": "Bloodborne" },
  { "main": "Cyberpunk 2077", "different": "Deus Ex" },
  { "main": "Metal Gear Solid", "different": "Splinter Cell" },
  { "main": "BioShock", "different": "Atomic Heart" },
  { "main": "Mass Effect", "different": "Dragon Age" },
  { "main": "Gran Turismo", "different": "Forza Motorsport" },
  { "main": "Need for Speed", "different": "Burnout" },
  { "main": "Mario Kart", "different": "Crash Team Racing" },
  { "main": "Rocket League", "different": "LucidSound" },
  { "main": "Angry Birds", "different": "Cut the Rope" },
  { "main": "Clash of Clans", "different": "Clash Royale" },
  { "main": "Genshin Impact", "different": "Honkai: Star Rail" },
  { "main": "Stardew Valley", "different": "Harvest Moon" },
  { "main": "Terraria", "different": "Starbound" },
  { "main": "Hollow Knight", "different": "Ori and the Blind Forest" },
  { "main": "Cuphead", "different": "Mega Man" },
  { "main": "Undertale", "different": "Deltarune" },
  { "main": "Five Nights at Freddy's", "different": "Poppy Playtime" },
  { "main": "Age of Empires", "different": "Civilization" },
  { "main": "StarCraft", "different": "Warcraft III" },
  { "main": "Hearthstone", "different": "Magic: The Gathering" },
  { "main": "Guitar Hero", "different": "Rock Band" },
  { "main": "Just Dance", "different": "Dance Dance Revolution" },
  { "main": "Wii Sports", "different": "Nintendo Switch Sports" },
  { "main": "Portal", "different": "Half-Life" },
  { "main": "Left 4 Dead", "different": "Back 4 Blood" },
  { "main": "Rust", "different": "Ark: Survival Evolved" },
  { "main": "Sea of Thieves", "different": "Skull and Bones" },
  { "main": "Monster Hunter", "different": "Dauntless" },
  { "main": "Diablo", "different": "Path of Exile" },
  { "main": "World of Warcraft", "different": "Final Fantasy XIV" },
  { "main": "Spyro", "different": "Crash Bandicoot" },
  { "main": "Donkey Kong Country", "different": "Yoshi's Island" },
  { "main": "Metroid", "different": "Castlevania" },
  { "main": "Persona 5", "different": "Shin Megami Tensei V" },
  { "main": "Nier Automata", "different": "Bayonetta" },
  { "main": "Dragon Ball FighterZ", "different": "Marvel vs. Capcom" },
  { "main": "Tony Hawk's Pro Skater", "different": "Skate" },
  { "main": "Flight Simulator", "different": "Euro Truck Simulator" },
  { "main": "Steam", "different": "Epic Games Store" },
  { "main": "Twitch", "different": "Kick" },
  { "main": "Nvidia", "different": "AMD" },
  { "main": "Intel", "different": "Ryzen" },
  { "main": "Razer", "different": "Logitech" },
  { "main": "Oculus Rift", "different": "HTC Vive" },
  { "main": "GamePass", "different": "PS Plus" },
  { "main": "Link", "different": "Zelda" },
  { "main": "Kratos", "different": "Atreus" },
  { "main": "Ellie", "different": "Joel" },
  { "main": "Nathan Drake", "different": "Lara Croft" },
  { "main": "Geralt de Rivia", "different": "Ciri" },
  { "main": "Cloud Strife", "different": "Sephiroth" },
  { "main": "Leon S. Kennedy", "different": "Chris Redfield" },
  { "main": "Solid Snake", "different": "Big Boss" },
  { "main": "Sora", "different": "Riku" },
  { "main": "Bowser", "different": "Dr. Eggman" },
  { "main": "Luigi", "different": "Waluigi" },
  { "main": "Pikachu", "different": "Eevee" },
  { "main": "Charizard", "different": "Mewtwo" },
  { "main": "Sub-Zero", "different": "Scorpion" },
  { "main": "Ryu", "different": "Ken" },
  { "main": "Agent 47", "different": "Sam Fisher" }
]